<?xml version="1.0" encoding="UTF-8"?>
<akn:akomaNtoso xmlns:akn="http://docs.oasis-open.org/legaldocml/ns/akn/3.0">
  <akn:act name="dc-code">
    <akn:meta>
      <akn:identification source="#cosilico">
        <akn:FRBRWork>
          <akn:FRBRuri value="/akn/us-dc/code/38-2021.09"/>
          <akn:FRBRdate date="2025-12-31" name="retrieval"/>
          <akn:FRBRauthor href="#dc-council"/>
          <akn:FRBRcountry value="us-dc"/>
        </akn:FRBRWork>
        <akn:FRBRExpression>
          <akn:FRBRuri value="/akn/us-dc/code/38-2021.09/eng@2025"/>
          <akn:FRBRdate date="2025-12-31"/>
          <akn:FRBRauthor href="#cosilico"/>
          <akn:FRBRlanguage language="en"/>
        </akn:FRBRExpression>
      </akn:identification>
    </akn:meta>
    <akn:body>
      <akn:section eId="sec_38_2021_09">
        <akn:num>38-2021.09</akn:num>
        <akn:heading>Deferred annuity; annuity to survivors.</akn:heading>
<akn:subsection eId="subsec_38-2021_09_a">
      <akn:num>(a)</akn:num>
      <akn:content><akn:p>Should a teacher to whom this part applies, after completing 5 years of eligible service and before becoming eligible for retirement, become separated from the service, the teacher may elect to receive a deferred annuity, computed as provided in § 38-2021.05, beginning at the age of 62 years and terminating on the date of the teacher’s death; provided, that a teacher who becomes separated from the public schools of the District of Columbia for other than retirement purposes and who does not elect to receive a deferred annuity as provided for in this section shall receive as soon as practicable after separation the refund of deductions, deposits, or redeposits; provided further, that no teacher who shall withdraw the amount of the teacher’s deductions, deposits, or redeposits under this section shall, after reinstatement, be entitled to credit for previous service unless the teacher shall repay to the Custodian of Retirement Funds as defined in § 1-702(6), for deposit in the District of Columbia Teachers’ Retirement Fund, established by § 1-713(a), the amount withdrawn by him (including the interest thereon) plus interest computed in accordance with § 38-2021.24(c); and provided further, that the amount required to be so deposited may be paid by the teacher, if he so elects, in any number of monthly installments, not exceeding 100.</akn:p></akn:content>
    </akn:subsection><akn:subsection eId="subsec_38-2021_09_b">
      <akn:num>(b)</akn:num>
      <akn:content><akn:p></akn:p></akn:content>
    </akn:subsection><akn:subsection eId="subsec_38-2021_09_b_1">
      <akn:num>(b-1)</akn:num>
      <akn:content><akn:p>Effective as of January 1, 2007, benefits payable under this part shall not be paid until at least 30 days, or a shorter period as may be permitted by law, but no more than 180 days after a teacher’s receipt of required distribution notices and election forms pursuant to section 402(f) of the Internal Revenue Code. The notices must include a description of the teacher’s right, if any, to defer receipt of a distribution, the consequences of failing to defer receipt of the distribution, the relative value of optional forms of benefit, and other information as may be required by applicable regulations and guidance.</akn:p></akn:content>
    </akn:subsection><akn:subsection eId="subsec_38-2021_09_c">
      <akn:num>(c)</akn:num>
      <akn:content><akn:p>As used in this section:</akn:p></akn:content>
    </akn:subsection>
      </akn:section>
    </akn:body>
  </akn:act>
</akn:akomaNtoso>
