<?xml version="1.0" encoding="UTF-8"?>
<akn:akomaNtoso xmlns:akn="http://docs.oasis-open.org/legaldocml/ns/akn/3.0">
  <akn:act name="dc-code">
    <akn:meta>
      <akn:identification source="#cosilico">
        <akn:FRBRWork>
          <akn:FRBRuri value="/akn/us-dc/code/16-2388"/>
          <akn:FRBRdate date="2025-12-31" name="retrieval"/>
          <akn:FRBRauthor href="#dc-council"/>
          <akn:FRBRcountry value="us-dc"/>
        </akn:FRBRWork>
        <akn:FRBRExpression>
          <akn:FRBRuri value="/akn/us-dc/code/16-2388/eng@2025"/>
          <akn:FRBRdate date="2025-12-31"/>
          <akn:FRBRauthor href="#cosilico"/>
          <akn:FRBRlanguage language="en"/>
        </akn:FRBRExpression>
      </akn:identification>
    </akn:meta>
    <akn:body>
      <akn:section eId="sec_16_2388">
        <akn:num>16-2388</akn:num>
        <akn:heading>Adjudicatory hearings.</akn:heading>
<akn:subsection eId="subsec_16-2388_a">
      <akn:num>(a)</akn:num>
      <akn:content><akn:p>The court shall begin the adjudicatory hearing by determining whether all parties are present and whether proper notice of the hearing has been given. If a parent has been given proper notice but fails to appear, the court may proceed in the parent’s absence.</akn:p></akn:content>
    </akn:subsection><akn:subsection eId="subsec_16-2388_b">
      <akn:num>(b)</akn:num>
      <akn:content><akn:p>The court shall hear evidence presented by the moving party and the burden of proof shall rest upon the moving party.</akn:p></akn:content>
    </akn:subsection><akn:subsection eId="subsec_16-2388_c">
      <akn:num>(c)</akn:num>
      <akn:content><akn:p>Every party shall have the right to present evidence, to be heard in his or her own behalf, and to cross-examine witnesses called by another party.</akn:p></akn:content>
    </akn:subsection><akn:subsection eId="subsec_16-2388_d">
      <akn:num>(d)</akn:num>
      <akn:content><akn:p>All evidence which is relevant, material, and competent to the issues before the court shall be admitted.</akn:p></akn:content>
    </akn:subsection><akn:subsection eId="subsec_16-2388_e">
      <akn:num>(e)</akn:num>
      <akn:content><akn:p>Notwithstanding the provisions of sections 14-306 and 14-307, neither the spouse or domestic partner privilege nor the physician/client or mental health professional/client privilege shall be a ground for excluding evidence in any proceeding brought under this subchapter.</akn:p></akn:content>
    </akn:subsection><akn:subsection eId="subsec_16-2388_f">
      <akn:num>(f)</akn:num>
      <akn:content><akn:p>The court may enter, modify, or terminate a guardianship order after considering all of the evidence presented, including the Mayor’s report and recommendation, and after making a determination based upon a preponderance of the evidence that creation, modification, or termination of the guardianship order is in the child’s best interests. If the court does not find that sufficient grounds exist to create, modify, or terminate a guardianship order, the motion may be dismissed.</akn:p></akn:content>
    </akn:subsection>
      </akn:section>
    </akn:body>
  </akn:act>
</akn:akomaNtoso>
