<?xml version="1.0" encoding="UTF-8"?>
<akn:akomaNtoso xmlns:akn="http://docs.oasis-open.org/legaldocml/ns/akn/3.0">
  <akn:act name="dc-code">
    <akn:meta>
      <akn:identification source="#cosilico">
        <akn:FRBRWork>
          <akn:FRBRuri value="/akn/us-dc/code/31-5411"/>
          <akn:FRBRdate date="2025-12-31" name="retrieval"/>
          <akn:FRBRauthor href="#dc-council"/>
          <akn:FRBRcountry value="us-dc"/>
        </akn:FRBRWork>
        <akn:FRBRExpression>
          <akn:FRBRuri value="/akn/us-dc/code/31-5411/eng@2025"/>
          <akn:FRBRdate date="2025-12-31"/>
          <akn:FRBRauthor href="#cosilico"/>
          <akn:FRBRlanguage language="en"/>
        </akn:FRBRExpression>
      </akn:identification>
    </akn:meta>
    <akn:body>
      <akn:section eId="sec_31_5411">
        <akn:num>31-5411</akn:num>
        <akn:heading>Miscellaneous.</akn:heading>
<akn:subsection eId="subsec_31-5411_a">
      <akn:num>(a)</akn:num>
      <akn:content><akn:p>Nothing in this chapter shall be construed to reduce the liability for unpaid assessments of the insureds of an impaired or insolvent insurer operating under a plan with assessment liability.</akn:p></akn:content>
    </akn:subsection><akn:subsection eId="subsec_31-5411_b">
      <akn:num>(b)</akn:num>
      <akn:content><akn:p></akn:p></akn:content>
    </akn:subsection><akn:subsection eId="subsec_31-5411_c">
      <akn:num>(c)</akn:num>
      <akn:content><akn:p></akn:p></akn:content>
    </akn:subsection><akn:subsection eId="subsec_31-5411_c_1">
      <akn:num>(c-1)</akn:num>
      <akn:content><akn:p>As a creditor of the impaired or insolvent insurer as established in subsection (c) of this section and consistent with Chapter 13 of this title [ยง 31-1301 et seq.], the Association and other similar associations shall be entitled to receive a disbursement of assets out of the marshaled assets, as the assets become available to reimburse it, as a credit against contractual obligations under this chapter. If the liquidator has not, within 120 days of a final determination of insolvency of an insurer by the receivership court, made an application to the court for the approval of a proposal to disburse assets out of marshaled assets to guaranty associations having obligations because of the insolvency, then the Association shall be entitled to make application to the receivership court for approval of its own proposal to disburse the assets.</akn:p></akn:content>
    </akn:subsection><akn:subsection eId="subsec_31-5411_d">
      <akn:num>(d)</akn:num>
      <akn:content><akn:p></akn:p></akn:content>
    </akn:subsection><akn:subsection eId="subsec_31-5411_e">
      <akn:num>(e)</akn:num>
      <akn:content><akn:p></akn:p></akn:content>
    </akn:subsection>
      </akn:section>
    </akn:body>
  </akn:act>
</akn:akomaNtoso>
