<?xml version="1.0" encoding="UTF-8"?>
<akn:akomaNtoso xmlns:akn="http://docs.oasis-open.org/legaldocml/ns/akn/3.0">
  <akn:act name="dc-code">
    <akn:meta>
      <akn:identification source="#cosilico">
        <akn:FRBRWork>
          <akn:FRBRuri value="/akn/us-dc/code/2-1515.04"/>
          <akn:FRBRdate date="2025-12-31" name="retrieval"/>
          <akn:FRBRauthor href="#dc-council"/>
          <akn:FRBRcountry value="us-dc"/>
        </akn:FRBRWork>
        <akn:FRBRExpression>
          <akn:FRBRuri value="/akn/us-dc/code/2-1515.04/eng@2025"/>
          <akn:FRBRdate date="2025-12-31"/>
          <akn:FRBRauthor href="#cosilico"/>
          <akn:FRBRlanguage language="en"/>
        </akn:FRBRExpression>
      </akn:identification>
    </akn:meta>
    <akn:body>
      <akn:section eId="sec_2_1515_04">
        <akn:num>2-1515.04</akn:num>
        <akn:heading>Duties.</akn:heading>
<akn:subsection eId="subsec_2-1515_04_1">
      <akn:num>(1)</akn:num>
      <akn:content><akn:p>Providing services for committed and detained youth and PINS that balance the need for rehabilitation and holding youth accountable for their actions in the context of public safety;</akn:p></akn:content>
    </akn:subsection><akn:subsection eId="subsec_2-1515_04_2">
      <akn:num>(2)</akn:num>
      <akn:content><akn:p>Facilitating and enhancing intra-District coordination of services and supports for youth in the juvenile justice system;</akn:p></akn:content>
    </akn:subsection><akn:subsection eId="subsec_2-1515_04_3">
      <akn:num>(3)</akn:num>
      <akn:content><akn:p>Establishing and adopting best practices standards for the provision of residential, restorative, and rehabilitative services to youth in the juvenile justice system consistent with the standards of the American Correctional Association or those of another nationally accepted accrediting body;</akn:p></akn:content>
    </akn:subsection><akn:subsection eId="subsec_2-1515_04_4">
      <akn:num>(4)</akn:num>
      <akn:content><akn:p>Employing a cadre of juvenile justice professionals who are highly skilled and experienced with the principles, goals, and the latest advancements of juvenile rehabilitation and treatment provision;</akn:p></akn:content>
    </akn:subsection><akn:subsection eId="subsec_2-1515_04_5">
      <akn:num>(5)</akn:num>
      <akn:content><akn:p>Establishing through contracts, provider agreements, human care agreements, grants, memoranda of agreement or understanding, or other binding agreements a system of secure and community-based facilities and rehabilitative services with governmental bodies, public and private agencies, institutions, and organizations, for youth that will provide intervention, individualized assessments, continuum of services, safety, and security;</akn:p></akn:content>
    </akn:subsection><akn:subsection eId="subsec_2-1515_04_6">
      <akn:num>(6)</akn:num>
      <akn:content><akn:p>Establishing a system that constantly reviews a youth’s individual strengths, needs, and rehabilitative progress and ensures placement within a continuum of least restrictive settings within secure facilities and the community;</akn:p></akn:content>
    </akn:subsection><akn:subsection eId="subsec_2-1515_04_7">
      <akn:num>(7)</akn:num>
      <akn:content><akn:p>Assessing the risks and needs of youth, and determining and providing the services needed for treatment for substance abuse and other services;</akn:p></akn:content>
    </akn:subsection><akn:subsection eId="subsec_2-1515_04_8">
      <akn:num>(8)</akn:num>
      <akn:content><akn:p>Developing and maintaining a system with other governmental and private agencies to identify, locate, and retrieve youth who are under the care, custody, or supervision of the Department, who have absconded from an assigned secure governmental facility, or community shelter home, group home, residential facility, or foster care placement;</akn:p></akn:content>
    </akn:subsection><akn:subsection eId="subsec_2-1515_04_9">
      <akn:num>(9)</akn:num>
      <akn:content><akn:p>Developing and maintaining state-of-the-art systems to monitor accountability and to enhance performance for all Department programs, services, and facilities;</akn:p></akn:content>
    </akn:subsection><akn:subsection eId="subsec_2-1515_04_10">
      <akn:num>(10)</akn:num>
      <akn:content><akn:p>Developing and maintaining an ongoing training program for employees that ensures continuous development of expertise in juvenile justice service delivery;</akn:p></akn:content>
    </akn:subsection><akn:subsection eId="subsec_2-1515_04_11">
      <akn:num>(11)</akn:num>
      <akn:content><akn:p>Taking a leadership role in the provision of training and technical assistance to non-governmental juvenile justice service providers that fosters the development of high-quality, comprehensive, cost-effective, and culturally competent delinquency prevention and juvenile rehabilitative services for the youth and their families;</akn:p></akn:content>
    </akn:subsection><akn:subsection eId="subsec_2-1515_04_12">
      <akn:num>(12)</akn:num>
      <akn:content><akn:p>Developing and maintaining a capital improvement, licensing, and regulating program that ensures governmental and private institutions maintain up-to-date residential facilities, group homes, and shelter facilities to serve the safety, the security, and the rehabilitative needs of youth in the juvenile justice system;</akn:p></akn:content>
    </akn:subsection><akn:subsection eId="subsec_2-1515_04_13">
      <akn:num>(13)</akn:num>
      <akn:content><akn:p>Enforcing all laws, rules, regulations, court orders, policies, and procedures necessary and appropriate to accomplish the duties of the Department; and</akn:p></akn:content>
    </akn:subsection><akn:subsection eId="subsec_2-1515_04_14">
      <akn:num>(14)</akn:num>
      <akn:content><akn:p>Conducting a behavioral health screening and assessment as required in § 2-1515.04a.</akn:p></akn:content>
    </akn:subsection>
      </akn:section>
    </akn:body>
  </akn:act>
</akn:akomaNtoso>
