<?xml version="1.0" encoding="UTF-8"?>
<akn:akomaNtoso xmlns:akn="http://docs.oasis-open.org/legaldocml/ns/akn/3.0">
  <akn:act name="dc-code">
    <akn:meta>
      <akn:identification source="#cosilico">
        <akn:FRBRWork>
          <akn:FRBRuri value="/akn/us-dc/code/2-218.41"/>
          <akn:FRBRdate date="2025-12-31" name="retrieval"/>
          <akn:FRBRauthor href="#dc-council"/>
          <akn:FRBRcountry value="us-dc"/>
        </akn:FRBRWork>
        <akn:FRBRExpression>
          <akn:FRBRuri value="/akn/us-dc/code/2-218.41/eng@2025"/>
          <akn:FRBRdate date="2025-12-31"/>
          <akn:FRBRauthor href="#cosilico"/>
          <akn:FRBRlanguage language="en"/>
        </akn:FRBRExpression>
      </akn:identification>
    </akn:meta>
    <akn:body>
      <akn:section eId="sec_2_218_41">
        <akn:num>2-218.41</akn:num>
        <akn:heading>Goals for District agencies with respect to contracting and procurement.</akn:heading>
<akn:subsection eId="subsec_2-218_41_a">
      <akn:num>(a)</akn:num>
      <akn:content><akn:p>Each agency, including an agency that contracts or procures in whole or in part through the Office of Contracting and Procurement, shall exercise its contracting and procurement authority so as to meet, on an annual basis, the goal of procuring and contracting 50% of the dollar volume of its expendable budget to qualified small business enterprises.</akn:p></akn:content>
    </akn:subsection><akn:subsection eId="subsec_2-218_41_a_1">
      <akn:num>(a-1)</akn:num>
      <akn:content><akn:p>If the agency determines in writing that there are not at least 2 qualified small business enterprises, the agency may use any qualified certified business enterprises to fulfill the requirements of subsection (a) of this section.</akn:p></akn:content>
    </akn:subsection><akn:subsection eId="subsec_2-218_41_a_2">
      <akn:num>(a-2)</akn:num>
      <akn:content><akn:p></akn:p></akn:content>
    </akn:subsection><akn:subsection eId="subsec_2-218_41_a_3">
      <akn:num>(a-3)</akn:num>
      <akn:content><akn:p>By October 1, 2015, and no later than October 1 of each succeeding year, an agency shall submit to the Department:</akn:p></akn:content>
    </akn:subsection><akn:subsection eId="subsec_2-218_41_b">
      <akn:num>(b)</akn:num>
      <akn:content><akn:p>Repealed.</akn:p></akn:content>
    </akn:subsection><akn:subsection eId="subsec_2-218_41_c">
      <akn:num>(c)</akn:num>
      <akn:content><akn:p>The provisions of this subchapter relating to contracting and subcontracting goals and requirements shall be applicable to every government-assisted project unless the Department, by regulation, establishes a specific exemption for a particular type or class of government-assisted project.</akn:p></akn:content>
    </akn:subsection>
      </akn:section>
    </akn:body>
  </akn:act>
</akn:akomaNtoso>
